mdsmosaic/__init__.py
mdsmosaic/epix.py
mdsmosaic/gpas.py
mdsmosaic/helpers.py
mdsmosaic/model.py
mdsmosaic/schema.py
mdsmosaic-0.1.3.dist-info/LICENSE
mdsmosaic-0.1.3.dist-info/METADATA
mdsmosaic-0.1.3.dist-info/WHEEL
mdsmosaic-0.1.3.dist-info/top_level.txt
mdsmosaic-0.1.3.dist-info/RECORD
