Metadata-Version: 2.1
Name: mdsmosaic
Version: 0.1.3
Summary: Client utilities for the MOSAIC suite
Home-page: https://hub.docker.com/u/mds4ul
Author: Maximilian Jugl
Author-email: jugl@hs-mittweida.de
License: MIT
Platform: UNKNOWN
Classifier: Development Status :: 3 - Alpha
Classifier: License :: OSI Approved :: MIT License
Classifier: Natural Language :: English
Classifier: Operating System :: OS Independent
Classifier: Programming Language :: Python :: 3
Classifier: Programming Language :: Python :: 3.7
Classifier: Programming Language :: Python :: 3.8
Classifier: Programming Language :: Python :: 3.9
Classifier: Programming Language :: Python :: 3.10
Classifier: Topic :: Scientific/Engineering :: Information Analysis
Classifier: Topic :: Software Development :: Libraries
Classifier: Typing :: Typed
License-File: LICENSE
Requires-Dist: marshmallow
Requires-Dist: zeep
